RPA/core/__init__.py
RPA/core/certificates.py
RPA/core/decorators.py
RPA/core/geometry.py
RPA/core/helpers.py
RPA/core/locators/__init__.py
RPA/core/locators/containers.py
RPA/core/locators/database.py
RPA/core/locators/literal.py
RPA/core/locators/syntax.py
RPA/core/logger.py
RPA/core/notebook.py
RPA/core/robocorp.py
RPA/core/types.py
RPA/core/vendor/__init__.py
RPA/core/vendor/deco.py
RPA/core/vendor/robotlibcore.py
RPA/core/webdriver.py
RPA/core/windows/__init__.py
RPA/core/windows/action.py
RPA/core/windows/context.py
RPA/core/windows/elements.py
RPA/core/windows/helpers.py
RPA/core/windows/inspect.py
RPA/core/windows/locators.py
RPA/core/windows/window.py
rpaframework_core-12.0.0.dist-info/LICENSE
rpaframework_core-12.0.0.dist-info/METADATA
rpaframework_core-12.0.0.dist-info/WHEEL
rpaframework_core-12.0.0.dist-info/RECORD
